useis/__init__.py
useis/ai/__init__.py
useis/ai/create-picking_dataset.py
useis/ai/create_classification_dataset.py
useis/ai/database.py
useis/ai/dataset.py
useis/ai/event_type_lookup.py
useis/ai/model.py
useis/ai/params.py
useis/ai/resnet1d.py
useis/ai/spectrogram.py
useis/clients/__init__.py
useis/clients/test_data.py
useis/core/__init__.py
useis/core/project_manager.py
useis/core/projection.py
useis/examples/classifier/.gitignore
useis/examples/classifier/__init__.py
useis/examples/classifier/classifier.py
useis/examples/classifier/example.ipynb
useis/examples/picker/.gitignore
useis/examples/picker/ai_picker.py
useis/processors/__init__.py
useis/processors/beamforming.py
useis/processors/data_extractor.py
useis/processors/file_manager.py
useis/processors/magnitude.py
useis/processors/nlloc.py
useis/processors/picker.py
useis/processors/ray_tracer.py
useis/processors/simple_magnitude.py
useis/processors/tomography.py
useis/sandbox/__init__.py
useis/sandbox/ai_picker/train_picker.py
useis/sandbox/demo_kafka/Dockerfile
useis/sandbox/demo_kafka/__init__.py
useis/sandbox/demo_kafka/consumer.py
useis/sandbox/demo_kafka/demo_kafka.py
useis/sandbox/demo_kafka/docker-compose.yml
useis/sandbox/demo_kafka/producer.py
useis/sandbox/event_classification/00_create_training_dataset.py
useis/sandbox/event_classification/01_train.py
useis/sandbox/event_classification/02_test.py
useis/sandbox/event_classification/__init__.py
useis/sandbox/event_classification/event_type_lookup.py
useis/sandbox/event_classification/inventory/OT.xml
useis/sandbox/event_classification/inventory/OT_old.xml
useis/sandbox/event_classification/inventory/__init__.py
useis/sandbox/event_classification/inventory/update_inventory.py
useis/sandbox/event_classification/velocity.py
useis/sandbox/tomography/Tomography.ipynb
useis/sandbox/tomography/test_tomography.py
useis/scripts/__init__.py
useis/scripts/ai/create-picking_dataset.py
useis/scripts/ai/create_classification_dataset.py
useis-1.2.1.dist-info/LICENSE
useis-1.2.1.dist-info/METADATA
useis-1.2.1.dist-info/WHEEL
useis-1.2.1.dist-info/entry_points.txt
useis-1.2.1.dist-info/RECORD
