Metadata-Version: 2.1
Name: useis
Version: 1.2.1
Summary: 
License: MIT
Author: jpmercier
Author-email: jpmercier01@gmail.com
Requires-Python: >=3.9,<4.0
Classifier: License :: OSI Approved :: MIT License
Classifier: Programming Language :: Python :: 3
Classifier: Programming Language :: Python :: 3.9
Classifier: Programming Language :: Python :: 3.10
Classifier: Programming Language :: Python :: 3.11
Provides-Extra: docs
Requires-Dist: Sphinx (>=4.1.2,<5.0.0) ; extra == "docs"
Requires-Dist: dynaconf (>=3.1.4,<4.0.0)
Requires-Dist: fastapi (>=0.68.1,<0.69.0)
Requires-Dist: furl (>=2.1.2,<3.0.0)
Requires-Dist: myst-parser (>=0.15.1,<0.16.0)
Requires-Dist: numpy (>=1.3.0,<2.0.0)
Requires-Dist: pillow (>=9.4.0,<10.0.0)
Requires-Dist: pydantic (>=1.8.2,<2.0.0)
Requires-Dist: pyproj (==3.4.1)
Requires-Dist: python-multipart (>=0.0.5,<0.0.6)
Requires-Dist: rinohtype (>=0.5.3,<0.6.0)
Requires-Dist: scikit-learn (>=1.0.1,<2.0.0)
Requires-Dist: sphinx-rtd-theme (>=0.5.2,<0.6.0) ; extra == "docs"
Requires-Dist: uquake (>=1.4.9,<2.0.0)
Requires-Dist: uvicorn (>=0.15.0,<0.16.0)
